{
  "repositories": {
    "PLAIF-dev/sw_controller_backend": {
      "additions": 169962,
      "deletions": 118865,
      "last_updated": "2025-04-04T00:51:45.744841Z",
      "languages": {
        "C++": {
          "additions": 148534,
          "deletions": 103879
        },
        "CMake": {
          "additions": 17213,
          "deletions": 12038
        },
        "Shell": {
          "additions": 2492,
          "deletions": 1743
        },
        "Dockerfile": {
          "additions": 1720,
          "deletions": 1203
        }
      }
    },
    "PLAIF-dev/sw_cylinder_control_ui": {
      "additions": 0,
      "deletions": 0,
      "last_updated": "2025-04-04T00:51:50.278585Z",
      "languages": {
        "Unknown": {
          "additions": 0,
          "deletions": 0
        }
      }
    },
    "PLAIF-dev/sw_order_backend": {
      "additions": 160152,
      "deletions": 908,
      "last_updated": "2025-04-04T00:51:52.592288Z",
      "languages": {
        "C++": {
          "additions": 133052,
          "deletions": 754
        },
        "CMake": {
          "additions": 21599,
          "deletions": 122
        },
        "Shell": {
          "additions": 3798,
          "deletions": 21
        },
        "C": {
          "additions": 1701,
          "deletions": 9
        }
      }
    },
    "PLAIF-dev/mo_utility": {
      "additions": 641,
      "deletions": 0,
      "last_updated": "2025-04-04T00:51:57.086020Z",
      "languages": {
        "C++": {
          "additions": 394,
          "deletions": 0
        },
        "CMake": {
          "additions": 231,
          "deletions": 0
        },
        "Shell": {
          "additions": 14,
          "deletions": 0
        }
      }
    },
    "PLAIF-dev/sw_authentication": {
      "additions": 4492,
      "deletions": 774,
      "last_updated": "2025-04-04T00:52:03.736897Z",
      "languages": {
        "C++": {
          "additions": 4070,
          "deletions": 701
        },
        "CMake": {
          "additions": 191,
          "deletions": 33
        },
        "Cython": {
          "additions": 114,
          "deletions": 19
        },
        "Python": {
          "additions": 57,
          "deletions": 9
        },
        "C": {
          "additions": 33,
          "deletions": 5
        },
        "Shell": {
          "additions": 24,
          "deletions": 4
        }
      }
    },
    "PLAIF-dev/vs_handeye_calibration": {
      "additions": 163,
      "deletions": 26,
      "last_updated": "2025-04-04T00:52:10.450492Z",
      "languages": {
        "Unknown": {
          "additions": 163,
          "deletions": 26
        }
      }
    },
    "PLAIF-dev/sw_plaif_ui": {
      "additions": 0,
      "deletions": 0,
      "last_updated": "2025-04-04T00:52:23.676154Z",
      "languages": {
        "Unknown": {
          "additions": 0,
          "deletions": 0
        }
      }
    },
    "PLAIF-dev/sw_binpicking_gui_web": {
      "additions": 0,
      "deletions": 0,
      "last_updated": "2025-04-04T00:52:26.013941Z",
      "languages": {
        "Unknown": {
          "additions": 0,
          "deletions": 0
        }
      }
    },
    "PLAIF-dev/march_template": {
      "additions": 1305,
      "deletions": 59,
      "last_updated": "2025-04-04T00:52:32.777718Z",
      "languages": {
        "CMake": {
          "additions": 1055,
          "deletions": 47
        },
        "C++": {
          "additions": 249,
          "deletions": 11
        }
      }
    },
    "PLAIF-dev/core_msg_desc": {
      "additions": 3166,
      "deletions": 1566,
      "last_updated": "2025-04-04T00:52:41.685516Z",
      "languages": {
        "Shell": {
          "additions": 3166,
          "deletions": 1566
        }
      }
    },
    "PLAIF-dev/core_data_backup": {
      "additions": 0,
      "deletions": 0,
      "last_updated": "2025-04-04T00:52:48.378906Z",
      "languages": {
        "Python": {
          "additions": 0,
          "deletions": 0
        }
      }
    },
    "PLAIF-dev/sw_ipc": {
      "additions": 125363,
      "deletions": 73143,
      "last_updated": "2025-04-04T00:54:02.053273Z",
      "languages": {
        "C++": {
          "additions": 79252,
          "deletions": 46239
        },
        "Python": {
          "additions": 33896,
          "deletions": 19776
        },
        "Cython": {
          "additions": 8795,
          "deletions": 5131
        },
        "CMake": {
          "additions": 3040,
          "deletions": 1774
        },
        "Shell": {
          "additions": 198,
          "deletions": 115
        },
        "Dockerfile": {
          "additions": 168,
          "deletions": 98
        },
        "C": {
          "additions": 11,
          "deletions": 6
        }
      }
    },
    "PLAIF-dev/sw_binpicking_backend": {
      "additions": 1419,
      "deletions": 1377,
      "last_updated": "2025-04-04T00:54:06.532239Z",
      "languages": {
        "Unknown": {
          "additions": 1419,
          "deletions": 1377
        }
      }
    },
    "PLAIF-dev/march_data": {
      "additions": 2487,
      "deletions": 149,
      "last_updated": "2025-04-04T00:54:28.816867Z",
      "languages": {
        "C++": {
          "additions": 2033,
          "deletions": 121
        },
        "CMake": {
          "additions": 453,
          "deletions": 27
        }
      }
    },
    "gunjae-yoon/grpc_cpp_example": {
      "additions": 698,
      "deletions": 62,
      "last_updated": "2025-04-04T00:54:33.203291Z",
      "languages": {
        "C++": {
          "additions": 655,
          "deletions": 58
        },
        "CMake": {
          "additions": 34,
          "deletions": 3
        },
        "Shell": {
          "additions": 8,
          "deletions": 0
        }
      }
    },
    "PLAIF-dev/sw_march_modules": {
      "additions": 26846,
      "deletions": 15073,
      "last_updated": "2025-04-04T00:54:35.566414Z",
      "languages": {
        "C++": {
          "additions": 23191,
          "deletions": 13021
        },
        "CMake": {
          "additions": 2967,
          "deletions": 1666
        },
        "Shell": {
          "additions": 566,
          "deletions": 318
        },
        "Python": {
          "additions": 120,
          "deletions": 67
        }
      }
    },
    "PLAIF-dev/sw_binpicking_gui": {
      "additions": 2,
      "deletions": 2,
      "last_updated": "2025-04-04T00:54:42.223427Z",
      "languages": {
        "Unknown": {
          "additions": 2,
          "deletions": 2
        }
      }
    },
    "PLAIF-dev/sw_package_server": {
      "additions": 1969,
      "deletions": 440,
      "last_updated": "2025-04-04T00:56:54.008067Z",
      "languages": {
        "C++": {
          "additions": 1720,
          "deletions": 384
        },
        "Shell": {
          "additions": 171,
          "deletions": 38
        },
        "CMake": {
          "additions": 76,
          "deletions": 17
        }
      }
    },
    "PLAIF-dev/.github": {
      "additions": 17,
      "deletions": 1,
      "last_updated": "2025-04-04T00:56:58.493173Z",
      "languages": {
        "Unknown": {
          "additions": 17,
          "deletions": 1
        }
      }
    },
    "gunjae-yoon/github-template": {
      "additions": 401,
      "deletions": 34,
      "last_updated": "2025-04-04T00:57:00.769110Z",
      "languages": {
        "Shell": {
          "additions": 207,
          "deletions": 17
        },
        "CMake": {
          "additions": 193,
          "deletions": 16
        }
      }
    },
    "gunjae-yoon/ipc-benchmark": {
      "additions": 2237,
      "deletions": 555,
      "last_updated": "2025-04-04T00:57:05.258841Z",
      "languages": {
        "C++": {
          "additions": 1863,
          "deletions": 462
        },
        "CMake": {
          "additions": 264,
          "deletions": 65
        },
        "Shell": {
          "additions": 108,
          "deletions": 26
        }
      }
    },
    "PLAIF-dev/sw_pickpose_define_module": {
      "additions": 0,
      "deletions": 0,
      "last_updated": "2025-04-04T00:57:11.914696Z",
      "languages": {
        "Unknown": {
          "additions": 0,
          "deletions": 0
        }
      }
    },
    "PLAIF-dev/core_collision_checker": {
      "additions": 0,
      "deletions": 0,
      "last_updated": "2025-04-04T00:57:47.552304Z",
      "languages": {
        "Python": {
          "additions": 0,
          "deletions": 0
        }
      }
    },
    "gunjae-yoon/perf_cpp_to_python": {
      "additions": 624,
      "deletions": 175,
      "last_updated": "2025-04-04T00:57:51.962300Z",
      "languages": {
        "C++": {
          "additions": 267,
          "deletions": 74
        },
        "Python": {
          "additions": 233,
          "deletions": 65
        },
        "CMake": {
          "additions": 63,
          "deletions": 17
        },
        "Cython": {
          "additions": 60,
          "deletions": 16
        }
      }
    },
    "gunjae-yoon/event-handling-benchmark": {
      "additions": 1719,
      "deletions": 344,
      "last_updated": "2025-04-04T00:57:58.487513Z",
      "languages": {
        "C++": {
          "additions": 1560,
          "deletions": 312
        },
        "CMake": {
          "additions": 150,
          "deletions": 30
        },
        "C": {
          "additions": 7,
          "deletions": 1
        }
      }
    },
    "PLAIF-dev/mo_kinematics": {
      "additions": 2040,
      "deletions": 1220,
      "last_updated": "2025-04-04T00:58:31.711154Z",
      "languages": {
        "C++": {
          "additions": 1561,
          "deletions": 933
        },
        "CMake": {
          "additions": 416,
          "deletions": 249
        },
        "Shell": {
          "additions": 62,
          "deletions": 37
        }
      }
    },
    "PLAIF-dev/sw_debian_repo": {
      "additions": 886,
      "deletions": 73,
      "last_updated": "2025-04-04T00:58:34.135640Z",
      "languages": {
        "Shell": {
          "additions": 497,
          "deletions": 40
        },
        "Python": {
          "additions": 315,
          "deletions": 25
        },
        "Dockerfile": {
          "additions": 63,
          "deletions": 5
        },
        "Makefile": {
          "additions": 10,
          "deletions": 0
        }
      }
    },
    "PLAIF-dev/sw_plaif_dev_tool": {
      "additions": 0,
      "deletions": 0,
      "last_updated": "2025-04-04T00:58:43.036428Z",
      "languages": {
        "Unknown": {
          "additions": 0,
          "deletions": 0
        }
      }
    },
    "PLAIF-dev/sw_march": {
      "additions": 11090,
      "deletions": 4070,
      "last_updated": "2025-04-04T00:58:58.348245Z",
      "languages": {
        "C++": {
          "additions": 9426,
          "deletions": 3459
        },
        "CMake": {
          "additions": 1663,
          "deletions": 610
        }
      }
    },
    "PLAIF-dev/core_piece_picking_msg": {
      "additions": 582,
      "deletions": 26,
      "last_updated": "2025-04-04T00:59:00.715533Z",
      "languages": {
        "Python": {
          "additions": 461,
          "deletions": 20
        },
        "Shell": {
          "additions": 120,
          "deletions": 5
        }
      }
    },
    "PLAIF-dev/vs_cameramanager": {
      "additions": 0,
      "deletions": 0,
      "last_updated": "2025-04-04T00:59:03.053093Z",
      "languages": {
        "Python": {
          "additions": 0,
          "deletions": 0
        }
      }
    },
    "gunjae-yoon/modular-architecture": {
      "additions": 1157,
      "deletions": 238,
      "last_updated": "2025-04-04T00:59:07.465906Z",
      "languages": {
        "C++": {
          "additions": 746,
          "deletions": 153
        },
        "CMake": {
          "additions": 410,
          "deletions": 84
        }
      }
    },
    "PLAIF-dev/sw_simulator": {
      "additions": 0,
      "deletions": 0,
      "last_updated": "2025-04-04T00:59:09.837089Z",
      "languages": {
        "Unknown": {
          "additions": 0,
          "deletions": 0
        }
      }
    },
    "PLAIF-dev/vs_piecepicking": {
      "additions": 0,
      "deletions": 0,
      "last_updated": "2025-04-04T00:59:14.414328Z",
      "languages": {
        "Python": {
          "additions": 0,
          "deletions": 0
        },
        "Dockerfile": {
          "additions": 0,
          "deletions": 0
        },
        "Shell": {
          "additions": 0,
          "deletions": 0
        }
      }
    },
    "PLAIF-dev/sw_assembly_backend": {
      "additions": 0,
      "deletions": 0,
      "last_updated": "2025-04-04T00:59:21.094299Z",
      "languages": {
        "Unknown": {
          "additions": 0,
          "deletions": 0
        }
      }
    },
    "gunjae-yoon/enad-cade": {
      "additions": 27695,
      "deletions": 0,
      "last_updated": "2025-04-04T00:59:29.851919Z",
      "languages": {
        "C++": {
          "additions": 26776,
          "deletions": 0
        },
        "Shell": {
          "additions": 296,
          "deletions": 0
        },
        "Python": {
          "additions": 285,
          "deletions": 0
        },
        "C": {
          "additions": 148,
          "deletions": 0
        },
        "CMake": {
          "additions": 116,
          "deletions": 0
        },
        "Batchfile": {
          "additions": 71,
          "deletions": 0
        }
      }
    },
    "PLAIF-dev/sw_package_manager": {
      "additions": 9840,
      "deletions": 4150,
      "last_updated": "2025-04-04T01:00:21.815302Z",
      "languages": {
        "C++": {
          "additions": 8636,
          "deletions": 3642
        },
        "Shell": {
          "additions": 926,
          "deletions": 390
        },
        "CMake": {
          "additions": 276,
          "deletions": 116
        }
      }
    },
    "gunjae-yoon/pcap": {
      "additions": 129,
      "deletions": 0,
      "last_updated": "2025-04-04T01:00:24.094461Z",
      "languages": {
        "Python": {
          "additions": 129,
          "deletions": 0
        }
      }
    },
    "PLAIF-dev/prod_piece_picking": {
      "additions": 1048,
      "deletions": 143,
      "last_updated": "2025-04-04T01:00:26.423765Z",
      "languages": {
        "Dockerfile": {
          "additions": 788,
          "deletions": 107
        },
        "Makefile": {
          "additions": 259,
          "deletions": 35
        }
      }
    },
    "PLAIF-dev/mo_robot_data": {
      "additions": 1839,
      "deletions": 102,
      "last_updated": "2025-04-04T01:00:33.053868Z",
      "languages": {
        "C++": {
          "additions": 1148,
          "deletions": 63
        },
        "CMake": {
          "additions": 594,
          "deletions": 32
        },
        "C": {
          "additions": 61,
          "deletions": 3
        },
        "Shell": {
          "additions": 34,
          "deletions": 1
        }
      }
    },
    "PLAIF-dev/sw_order_picking_gui": {
      "additions": 8,
      "deletions": 3,
      "last_updated": "2025-04-04T01:00:37.587264Z",
      "languages": {
        "Unknown": {
          "additions": 8,
          "deletions": 3
        }
      }
    },
    "PLAIF-dev/sw_package_daemon": {
      "additions": 2263,
      "deletions": 450,
      "last_updated": "2025-04-04T01:00:46.502901Z",
      "languages": {
        "C++": {
          "additions": 2059,
          "deletions": 409
        },
        "Shell": {
          "additions": 110,
          "deletions": 21
        },
        "CMake": {
          "additions": 93,
          "deletions": 18
        }
      }
    },
    "PLAIF-dev/sw_total_picking_gui": {
      "additions": 0,
      "deletions": 0,
      "last_updated": "2025-04-04T01:00:48.855452Z",
      "languages": {
        "Unknown": {
          "additions": 0,
          "deletions": 0
        }
      }
    },
    "PLAIF-dev/sw_picq_launcher": {
      "additions": 0,
      "deletions": 0,
      "last_updated": "2025-04-04T01:00:53.382029Z",
      "languages": {
        "Unknown": {
          "additions": 0,
          "deletions": 0
        }
      }
    },
    "gunjae-yoon/gunjae-yoon": {
      "additions": 2317,
      "deletions": 1942,
      "last_updated": "2025-04-04T01:00:59.979542Z",
      "languages": {
        "Shell": {
          "additions": 1080,
          "deletions": 905
        },
        "CMake": {
          "additions": 1007,
          "deletions": 844
        },
        "C": {
          "additions": 229,
          "deletions": 192
        }
      }
    },
    "PLAIF-dev/sw_piece_picking": {
      "additions": 0,
      "deletions": 0,
      "last_updated": "2025-04-04T01:01:02.338375Z",
      "languages": {
        "Unknown": {
          "additions": 0,
          "deletions": 0
        }
      }
    },
    "PLAIF-dev/sw_logger": {
      "additions": 8414,
      "deletions": 2628,
      "last_updated": "2025-04-04T01:01:09.050303Z",
      "languages": {
        "C++": {
          "additions": 5837,
          "deletions": 1823
        },
        "CMake": {
          "additions": 1322,
          "deletions": 413
        },
        "Python": {
          "additions": 731,
          "deletions": 228
        },
        "Cython": {
          "additions": 316,
          "deletions": 98
        },
        "Dockerfile": {
          "additions": 126,
          "deletions": 39
        },
        "Shell": {
          "additions": 79,
          "deletions": 24
        }
      }
    },
    "gunjae-yoon/jsoncpp_benchmark": {
      "additions": 1015,
      "deletions": 55,
      "last_updated": "2025-04-04T01:01:11.362791Z",
      "languages": {
        "C++": {
          "additions": 839,
          "deletions": 45
        },
        "CMake": {
          "additions": 149,
          "deletions": 8
        },
        "Shell": {
          "additions": 26,
          "deletions": 1
        }
      }
    },
    "PLAIF-dev/sw_os_generator": {
      "additions": 3034,
      "deletions": 124,
      "last_updated": "2025-04-04T01:01:13.682789Z",
      "languages": {
        "C++": {
          "additions": 2172,
          "deletions": 88
        },
        "Shell": {
          "additions": 597,
          "deletions": 24
        },
        "CMake": {
          "additions": 173,
          "deletions": 7
        },
        "Dockerfile": {
          "additions": 90,
          "deletions": 3
        }
      }
    },
    "PLAIF-dev/sw_package_service_message": {
      "additions": 733,
      "deletions": 162,
      "last_updated": "2025-04-04T01:01:20.389859Z",
      "languages": {
        "Shell": {
          "additions": 733,
          "deletions": 162
        }
      }
    },
    "PLAIF-dev/mo_forcecontroller": {
      "additions": 0,
      "deletions": 0,
      "last_updated": "2025-04-04T01:01:24.933835Z",
      "languages": {
        "Unknown": {
          "additions": 0,
          "deletions": 0
        }
      }
    },
    "PLAIF-dev/vs_dlmanager": {
      "additions": 0,
      "deletions": 0,
      "last_updated": "2025-04-04T01:01:52.951444Z",
      "languages": {
        "Python": {
          "additions": 0,
          "deletions": 0
        },
        "Makefile": {
          "additions": 0,
          "deletions": 0
        }
      }
    },
    "PLAIF-dev/sw_rbpodo_pipc": {
      "additions": 8634,
      "deletions": 3931,
      "last_updated": "2025-04-04T01:01:55.283790Z",
      "languages": {
        "C++": {
          "additions": 8082,
          "deletions": 3679
        },
        "CMake": {
          "additions": 466,
          "deletions": 212
        },
        "Shell": {
          "additions": 84,
          "deletions": 38
        }
      }
    },
    "PLAIF-dev/march_robot_io_codec": {
      "additions": 1262,
      "deletions": 1,
      "last_updated": "2025-04-04T01:01:59.791026Z",
      "languages": {
        "CMake": {
          "additions": 1029,
          "deletions": 0
        },
        "C++": {
          "additions": 232,
          "deletions": 0
        }
      }
    },
    "gunjae-yoon/guutil": {
      "additions": 1944,
      "deletions": 1775,
      "last_updated": "2025-04-04T01:02:02.065687Z",
      "languages": {
        "C++": {
          "additions": 1463,
          "deletions": 1336
        },
        "CMake": {
          "additions": 439,
          "deletions": 401
        },
        "Shell": {
          "additions": 40,
          "deletions": 37
        }
      }
    }
  }
}